atj_algotrading/__init__.py
atj_algotrading/backtester/__init__.py
atj_algotrading/mt5_trade_utils/__init__.py
atj_algotrading/mt5_webapi_client/__init__.py
atj_algotrading/trading_bot/__init__.py
atj_algotrading-0.0.16.dist-info/METADATA
atj_algotrading-0.0.16.dist-info/WHEEL
atj_algotrading-0.0.16.dist-info/licenses/LICENSE
atj_algotrading-0.0.16.dist-info/RECORD
