Metadata-Version: 2.3
Name: atj-algotrading
Version: 0.0.16
Summary: ATJ Trader's Package for Algo Trading & Backtesting
Project-URL: Homepage, https://github.com/atj-khactu/atj-algotrading-package
Project-URL: Issues, https://github.com/atj-khactu/atj-algotrading-package/issues
Author-email: Khac Tu Nguyen <khactu@atj-traders.com>
Classifier: Programming Language :: Python :: 3
Requires-Python: >=3.9
Requires-Dist: jupyter
Requires-Dist: numpy==1.26.4
Requires-Dist: pandas
Requires-Dist: plotly
Requires-Dist: requests
